axelrod_dojo/__init__.py
axelrod_dojo/utils.py
axelrod_dojo/version.py
axelrod_dojo/archetypes/__init__.py
axelrod_dojo/archetypes/fsm.py
axelrod_dojo-0.0.5.dist-info/DESCRIPTION.rst
axelrod_dojo-0.0.5.dist-info/METADATA
axelrod_dojo-0.0.5.dist-info/RECORD
axelrod_dojo-0.0.5.dist-info/WHEEL
axelrod_dojo-0.0.5.dist-info/metadata.json
axelrod_dojo-0.0.5.dist-info/top_level.txt
