Metadata-Version: 2.0
Name: axelrod-dojo
Version: 0.0.5
Summary: A library to train strategies for the Iterated Prisoners Dilemma
Home-page: UNKNOWN
Author: Marc Harper; Vince Knight; Martin Jones; Georgios Koutsovoulos
Author-email: UNKNOWN
License: The MIT License (MIT)
Platform: UNKNOWN
Classifier: Programming Language :: Python :: 3.5
Classifier: Programming Language :: Python :: 3.6
Classifier: Programming Language :: Python :: 3 :: Only
Requires-Python: >=3.0
Requires-Dist: axelrod (>=3.3.0)
Requires-Dist: pyswarm (>=0.6)
